CHANGELOG.rst
MANIFEST.in
README.rst
setup.py
qifparse/__init__.py
qifparse/parser.py
qifparse/qif.py
qifparse.egg-info/PKG-INFO
qifparse.egg-info/SOURCES.txt
qifparse.egg-info/dependency_links.txt
qifparse.egg-info/entry_points.txt
qifparse.egg-info/not-zip-safe
qifparse.egg-info/requires.txt
qifparse.egg-info/top_level.txt
qifparse/tests/__init__.py
qifparse/tests/file.qif
qifparse/tests/test_create.py
qifparse/tests/test_parse.py
qifparse/tests/transactions_only.qif