Metadata-Version: 1.1
Name: qifparse
Version: 0.5
Summary: a parser for Quicken interchange format files (.qif).
Home-page: https://github.com/giacomos/qifparse
Author: Giacomo Spettoli
Author-email: giacomo.spettoli@gmail.com
License: GPL
Keywords: qif,Quicken interchange format,file format
Platform: UNKNOWN
Classifier: Development Status :: 3 - Alpha
Classifier: Intended Audience :: Developers
Classifier: License :: OSI Approved :: GNU General Public License (GPL)
Classifier: Operating System :: OS Independent
Classifier: Programming Language :: Python :: 2.5
Classifier: Programming Language :: Python :: 2.6
Classifier: Programming Language :: Python :: 2.7
Classifier: Programming Language :: Python :: 3
Classifier: Programming Language :: Python :: 3.2
Classifier: Programming Language :: Python :: 3.3
Classifier: Programming Language :: Python
Classifier: Topic :: Software Development :: Libraries :: Python Modules
Classifier: Topic :: Utilities
